{
 "ticker": "META",
 "yf_symbol": "META",
 "meta": {
  "nombre": "Meta Platforms, Inc.",
  "sector": "Communication Services",
  "industria": "Internet Content & Information",
  "pais": "United States",
  "moneda": "USD",
  "exchange": "NMS"
 },
 "valuacion": {
  "pe": 21.915697,
  "forward_pe": 16.373953,
  "pb": 6.281649,
  "peg": 0.87,
  "ev_ebitda": 14.347
 },
 "rentabilidad": {
  "roe": 0.32930002,
  "roa": 0.16395001,
  "margen_operativo": 0.40617,
  "margen_neto": 0.32837
 },
 "dividendos": {
  "dividend_yield": 0.0034114167,
  "payout_ratio": 0.0764
 },
 "tamano": {
  "market_cap": 1530973782016.0,
  "enterprise_value": 1568191676416.0
 },
 "precio": {
  "actual": 603.12,
  "low_52w": 520.26,
  "high_52w": 796.25,
  "beta": 1.246
 },
 "proximos": {
  "earnings_date": "2026-07-29",
  "ex_div_date": "2026-06-15"
 },
 "obtenido": "2026-07-08"
}