{
 "ticker": "MSFT",
 "yf_symbol": "MSFT",
 "meta": {
  "nombre": "Microsoft Corporation",
  "sector": "Technology",
  "industria": "Software - Infrastructure",
  "pais": "United States",
  "moneda": "USD",
  "exchange": "NMS"
 },
 "valuacion": {
  "pe": 22.953487,
  "forward_pe": 19.8828,
  "pb": 6.9012313,
  "peg": 1.19,
  "ev_ebitda": 16.002
 },
 "rentabilidad": {
  "roe": 0.34013999,
  "roa": 0.14814,
  "margen_operativo": 0.46326,
  "margen_neto": 0.39341998
 },
 "dividendos": {
  "dividend_yield": 0.009105092,
  "payout_ratio": 0.20729999
 },
 "tamano": {
  "market_cap": 2859427430400.0,
  "enterprise_value": 2951647592448.0
 },
 "precio": {
  "actual": 384.93,
  "low_52w": 349.2,
  "high_52w": 555.45,
  "beta": 1.13
 },
 "proximos": {
  "earnings_date": "2026-07-29",
  "ex_div_date": "2026-08-20"
 },
 "obtenido": "2026-07-14"
}