{
 "ticker": "ORCL",
 "yf_symbol": "ORCL",
 "meta": {
  "nombre": "Oracle Corporation",
  "sector": "Technology",
  "industria": "Software - Infrastructure",
  "pais": "United States",
  "moneda": "USD",
  "exchange": "NYQ"
 },
 "valuacion": {
  "pe": 21.792454,
  "forward_pe": 11.666506,
  "pb": 9.743098,
  "peg": 0.71,
  "ev_ebitda": 16.091
 },
 "rentabilidad": {
  "roe": 0.53376,
  "roa": 0.06505,
  "margen_operativo": 0.36202,
  "margen_neto": 0.25368
 },
 "dividendos": {
  "dividend_yield": 0.016477179,
  "payout_ratio": 0.3431
 },
 "tamano": {
  "market_cap": 365963870208.0,
  "enterprise_value": 490671570944.0
 },
 "precio": {
  "actual": 127.05,
  "low_52w": 120.03,
  "high_52w": 345.72,
  "beta": 1.712
 },
 "proximos": {
  "earnings_date": "2026-09-09",
  "ex_div_date": "2026-07-10"
 },
 "obtenido": "2026-07-21"
}