{
 "ticker": "TMO",
 "yf_symbol": "TMO",
 "meta": {
  "nombre": "Thermo Fisher Scientific Inc.",
  "sector": "Healthcare",
  "industria": "Diagnostics & Research",
  "pais": "United States",
  "moneda": "USD",
  "exchange": "NYQ"
 },
 "valuacion": {
  "pe": 28.408342,
  "forward_pe": 18.990934,
  "pb": 3.7037566,
  "peg": 1.73,
  "ev_ebitda": 20.764
 },
 "rentabilidad": {
  "roe": 0.13523,
  "roa": 0.04997,
  "margen_operativo": 0.17892,
  "margen_neto": 0.15151
 },
 "dividendos": {
  "dividend_yield": 0.003362372,
  "payout_ratio": 0.0968
 },
 "tamano": {
  "market_cap": 192351272960.0,
  "enterprise_value": 234554540032.0
 },
 "precio": {
  "actual": 517.6,
  "low_52w": 403.36,
  "high_52w": 643.99,
  "beta": 0.868
 },
 "proximos": {
  "earnings_date": "2026-07-23",
  "ex_div_date": "2026-06-15"
 },
 "obtenido": "2026-07-06"
}